slip10/__init__.py
slip10/ripemd160.py
slip10/slip10.py
slip10/utils.py
slip10-1.0.1.dist-info/METADATA
slip10-1.0.1.dist-info/WHEEL
slip10-1.0.1.dist-info/RECORD
