Metadata-Version: 2.1
Name: slip10
Version: 1.0.1
Summary: A reference implementation of the SLIP-0010 specification, which generalizes the BIP-0032 derivation scheme for private and public key pairs in hierarchical deterministic wallets for the curves secp256k1, NIST P-256, ed25519 and curve25519.
Home-page: https://github.com/trezor/python-slip10
License: MIT
Keywords: bitcoin,slip10,hdwallet
Author: Antoine Poinsot
Author-email: darosior@protonmail.com
Maintainer: Andrew R. Kozlik
Maintainer-email: andrew.kozlik@satoshilabs.com
Requires-Python: >=3.8,<4.0
Classifier: License :: OSI Approved :: MIT License
Classifier: Programming Language :: Python :: 3
Classifier: Programming Language :: Python :: 3.8
Classifier: Programming Language :: Python :: 3.9
Classifier: Programming Language :: Python :: 3.10
Classifier: Programming Language :: Python :: 3.11
Classifier: Programming Language :: Python :: 3.12
Requires-Dist: base58 (>=2,<3)
Requires-Dist: cryptography
Requires-Dist: ecdsa
Project-URL: Repository, https://github.com/trezor/python-slip10
